{"config": {"view": {"continuousWidth": 400, "continuousHeight": 300}}, "hconcat": [{"data": {"url": "https://raw.githubusercontent.com/UIUC-iSchool-DataViz/is445_bcubcg_fall2022/main/data/building_inventory.csv"}, "mark": "rect", "encoding": {"color": {"aggregate": "count", "type": "quantitative"}, "x": {"bin": {"maxbins": 50}, "field": "Square Footage", "type": "quantitative"}, "y": {"field": "Congressional Full Name", "type": "nominal"}}, "height": 400}, {"data": {"url": "https://raw.githubusercontent.com/UIUC-iSchool-DataViz/is445_bcubcg_fall2022/main/data/building_inventory.csv"}, "mark": "bar", "encoding": {"color": {"value": "brown"}, "x": {"field": "Usage Description", "type": "nominal"}, "y": {"aggregate": "mean", "field": "Square Footage", "type": "quantitative"}}, "width": 600}], "$schema": "https://vega.github.io/schema/vega-lite/v4.17.0.json"}